{
  "updated": "2026-07-15T08:37:17Z",
  "items": [
    {
      "source": "bleepingcomputer",
      "title": "Microsoft: Some Dell PCs shut down after recent Windows updates",
      "link": "https://www.bleepingcomputer.com/news/microsoft/microsoft-some-dell-devices-shut-down-after-windows-update/",
      "date": "2026-07-15T08:26:48Z"
    },
    {
      "source": "bleepingcomputer",
      "title": "US charges alleged operators of Russian bulletproof hosting service",
      "link": "https://www.bleepingcomputer.com/news/security/us-charges-alleged-russian-bulletproof-hosting-service-operators/",
      "date": "2026-07-15T07:45:50Z"
    },
    {
      "source": "the hacker news",
      "title": "Two SonicWall SMA 1000 Zero-Days Exploited, One Could Enable Admin Commands",
      "link": "https://thehackernews.com/2026/07/two-sonicwall-sma-1000-zero-days.html",
      "date": "2026-07-15T05:30:21Z"
    },
    {
      "source": "bleepingcomputer",
      "title": "SonicWall warns of SMA1000 flaws exploited in zero-day attacks, patch now",
      "link": "https://www.bleepingcomputer.com/news/security/sonicwall-warns-of-sma1000-flaws-exploited-in-zero-day-attacks-patch-now/",
      "date": "2026-07-14T21:23:24Z"
    },
    {
      "source": "the hacker news",
      "title": "Microsoft Patches Record 622 Flaws, Including Two Zero-Days Under Active Attack",
      "link": "https://thehackernews.com/2026/07/microsoft-patches-record-622-flaws.html",
      "date": "2026-07-14T20:25:47Z"
    },
    {
      "source": "bleepingcomputer",
      "title": "Spanish Police take down €140 million cyber fraud ring, arrest four",
      "link": "https://www.bleepingcomputer.com/news/security/spanish-police-take-down-140-million-cyber-fraud-ring-arrest-four/",
      "date": "2026-07-14T20:23:09Z"
    },
    {
      "source": "bleepingcomputer",
      "title": "Nearly 300 GitHub repos pose as legit software to push malware",
      "link": "https://www.bleepingcomputer.com/news/security/nearly-300-github-repos-pose-as-legit-software-to-push-malware/",
      "date": "2026-07-14T19:15:17Z"
    },
    {
      "source": "bleepingcomputer",
      "title": "Microsoft releases Windows 10 KB5099539 extended security update",
      "link": "https://www.bleepingcomputer.com/news/microsoft/microsoft-releases-windows-10-kb5099539-extended-security-update/",
      "date": "2026-07-14T18:49:28Z"
    }
  ]
}
